setup.py
src/textool/__init__.py
src/textool/dataparse.py
src/textool/flistparse.py
src/textool/textool.py
src/textool.egg-info/PKG-INFO
src/textool.egg-info/SOURCES.txt
src/textool.egg-info/dependency_links.txt
src/textool.egg-info/entry_points.txt
src/textool.egg-info/requires.txt
src/textool.egg-info/top_level.txt