Metadata-Version: 1.0
Name: textool
Version: 1.0.0
Summary: A command line tool to convert TexturePacker file format.
Home-page: https://github.com/guobin8205/texturetool
Author: guobin
Author-email: guobin2013@hotmail.com
License: MIT License
Keywords: textool,texturepacker
Platform: UNKNOWN
